{
  "$id": "news_ap_chiki_100084",
  "$schema": "https://schema.yext.com/config/km/entity/v1",
  "primaryLocale": "ja",
  "content": {
    "c_ap_AuthorForDisplay": {
      "label": "JTB 地域ナビゲーター 沖縄担当 佐藤 政洋"
    },
    "c_ap_HeroImage": {
      "alternateText": "自然にやさしい、人にやさしい、誰もが笑顔になれるリゾートホテル【沖縄県　沖縄かりゆしビーチリゾート・オーシャンスパ】",
      "height": 814,
      "sourceUrl": "http://a.mktgcdn.com/p/-lR8ZTBzSLqdaJztdJ1rdS4oth4GTKGhvKvopfIvmYk/1200x814.jpg",
      "thumbnails": [
        {
          "height": 814,
          "url": "//a.mktgcdn.com/p-sandbox/-lR8ZTBzSLqdaJztdJ1rdS4oth4GTKGhvKvopfIvmYk/1200x814.jpg",
          "width": 1200
        },
        {
          "height": 420,
          "url": "//a.mktgcdn.com/p-sandbox/-lR8ZTBzSLqdaJztdJ1rdS4oth4GTKGhvKvopfIvmYk/619x420.jpg",
          "width": 619
        },
        {
          "height": 407,
          "url": "//a.mktgcdn.com/p-sandbox/-lR8ZTBzSLqdaJztdJ1rdS4oth4GTKGhvKvopfIvmYk/600x407.jpg",
          "width": 600
        },
        {
          "height": 133,
          "url": "//a.mktgcdn.com/p-sandbox/-lR8ZTBzSLqdaJztdJ1rdS4oth4GTKGhvKvopfIvmYk/196x133.jpg",
          "width": 196
        }
      ],
      "url": "http://a.mktgcdn.com/p-sandbox/-lR8ZTBzSLqdaJztdJ1rdS4oth4GTKGhvKvopfIvmYk/1200x814.jpg",
      "width": 1200
    },
    "c_ap_HeroImageCaption": "海を眺める高台のホテルで最高の休日を楽しむ",
    "c_ap_LinkContents": [
      {
        "linkText": "沖縄かりゆしビーチリゾート・オーシャンスパの宿泊プラン",
        "uRL": "https://www.jtb.co.jp/kokunai-hotel/htl/8707006/plan/"
      },
      {
        "linkText": "JTBスタッフのおすすめ旅\u0026おでかけ記事一覧",
        "uRL": "https://consultants.jtb.co.jp/articles"
      },
      {
        "linkText": "リモート相談ができるトラベルコンサルタント一覧",
        "uRL": "https://consultants.jtb.co.jp/index.html"
      },
      {
        "linkText": "沖縄旅行専門のリモート相談デスクはこちら",
        "uRL": "https://stores.jtb.co.jp/cc-0020"
      },
      {
        "linkText": "恩納村のホテル・旅館・宿",
        "uRL": "https://www.jtb.co.jp/kokunai-hotel/list/4731101/"
      },
      {
        "linkText": "沖縄旅行・ツアー・パック",
        "uRL": "https://www.jtb.co.jp/kokunai/area/okinawa/"
      }
    ],
    "c_ap_LinkSectionTitle": "関連リンク",
    "c_ap_PagesGeneration": true,
    "c_ap_ShortDescription": "高台のホテルから眺める海は、どこまでも青く輝いています。水深の浅いガーデンプールでは元気な子ども達の声が聞こえ、中庭のラグーンパティオのスパ施設では休日のひと時を優雅に楽しむ人々の姿が見られます。訪れる人の誰もが、それぞれに南国・沖縄を楽しみ、笑顔になれるホテル、それが「沖縄かりゆしビーチリゾート・オーシャンスパ」です。\n沖縄を代表するリゾート地・恩納村は、沖縄本島のほぼ中央部、西海岸沿いに細長く伸びる村。かりゆしビーチをはじめとするいくつもの白砂のビーチと、万座毛などの険しい断崖が織り成す海岸美が見事な風光明媚なところです。\n海を眺めて立ち並ぶ数多くのホテルは、どのホテルも設備の整ったリゾートホテル。約8万坪の緑豊かな敷地内に、円形のオーシャンタワーとウィングタワーの2棟が立つこのホテルは、そんなリゾートホテルの中でも人気のホテルです。すぐ隣の、渡り廊下で繋がっている「OKINAWA KARIYUSHI RESORT EXES ONNA」とともに、かりゆしホテルズのホテルの一つとしても親しまれています。",
    "c_ap_Tags": [
      "ビーチ",
      "スパ",
      "リゾート",
      "自然",
      "恩納村",
      "眺望",
      "海",
      "ガーデンプール",
      "JTBの一押しホテル"
    ],
    "c_ap_TagsLabel": "この記事に関連するタグ",
    "c_ap_Theme": [
      "ファミリー",
      "ハネムーン",
      "自然・山",
      "スポーツ観戦",
      "リゾート",
      "ホテル・旅館"
    ],
    "c_ap_Title": "自然にやさしい、人にやさしい、誰もが笑顔になれるリゾートホテル【沖縄県　沖縄かりゆしビーチリゾート・オーシャンスパ】",
    "c_linkedArea3News": [
      "okinawa_all"
    ],
    "c_metaDescription": "高台のホテルから眺める海は、どこまでも青く輝いています。水深の浅いガーデンプールでは元気な子ども達の声が聞こえ、中庭のラグーンパティオのスパ施設では休日のひと時を優雅に楽しむ人々の姿が見られます。訪れる人の誰…【おすすめの旅行情報はJTB】",
    "c_metaTitle": "自然にやさしい、人にやさしい、誰もが笑顔になれるリゾートホテル【沖縄県　沖縄かりゆしビーチリゾート・オーシャンスパ】 | JTBスタッフのおすすめ旅記事\u0026ブログ",
    "c_news_CTAs": [
      {
        "label": "沖縄かりゆしビーチリゾート・オーシャンスパを予約する",
        "link": "https://www.jtb.co.jp/kokunai-hotel/htl/8707006/plan/",
        "linkType": "URL"
      },
      {
        "label": "リモートでの旅行相談はこちら",
        "link": "https://consultants.jtb.co.jp/top#consultants",
        "linkType": "URL"
      },
      {
        "label": "JTB店舗・専門店への相談はこちら",
        "link": "https://consultants.jtb.co.jp/top#locator",
        "linkType": "URL"
      }
    ],
    "c_news_Contents": [
      {
        "description": "チェックインは、南国感漂う吹き抜けの大きなロビーをもつウィングタワーのフロントで。客室は、ラグーンパティオを囲むように円型に設計されたオーシャンタワーに、ツイン、トリプル、スイートの3タイプと、オーシャンビューとマウンテンビューがあって7タイプの客室が配されたウィングタワーの2棟に合わせて516室。ウィングタワーの客室には、4つのベッドを置いたフォースやエグゼクティブツイン、天蓋付きのエグゼクティブダブルなどが揃います。なかでも、2022年7月にリニューアルオープンした4室のかりゆしファミリールームは、「やんばるのツリーハウス」、「サブマリーンやんばるの海」をコンセプトに、室内に沖縄の森や海を再現したインスタ映えバッチリの色鮮やかでポップなデザインの客室。室内の二段ベッドスペースは子ども達に大人気です。ワンちゃんと一緒に休日を過ごしたいという方にはウィングタワー1階にペットルームもありますよ。琉球調の造りのシックな客室には、常設ゲージやフードボウルなどを完備。ワンちゃんの撮影用コスプレグッズの貸し出しで思い出が2倍に。オーシャンビューの客室なら、海に沈む夕日の景観は見逃さないように気を付けて。",
        "image": {
          "alternateText": "オーシャンタワーの落ち着きあるツインルーム",
          "height": 536,
          "sourceUrl": "http://a.mktgcdn.com/p/JarfwxHp7tlOo_yepcBx42uQxtIuKUqeIEyvFLsw18E/1000x536.jpg",
          "thumbnails": [
            {
              "height": 536,
              "url": "//a.mktgcdn.com/p-sandbox/JarfwxHp7tlOo_yepcBx42uQxtIuKUqeIEyvFLsw18E/1000x536.jpg",
              "width": 1000
            },
            {
              "height": 332,
              "url": "//a.mktgcdn.com/p-sandbox/JarfwxHp7tlOo_yepcBx42uQxtIuKUqeIEyvFLsw18E/619x332.jpg",
              "width": 619
            },
            {
              "height": 322,
              "url": "//a.mktgcdn.com/p-sandbox/JarfwxHp7tlOo_yepcBx42uQxtIuKUqeIEyvFLsw18E/600x322.jpg",
              "width": 600
            },
            {
              "height": 105,
              "url": "//a.mktgcdn.com/p-sandbox/JarfwxHp7tlOo_yepcBx42uQxtIuKUqeIEyvFLsw18E/196x105.jpg",
              "width": 196
            }
          ],
          "url": "http://a.mktgcdn.com/p-sandbox/JarfwxHp7tlOo_yepcBx42uQxtIuKUqeIEyvFLsw18E/1000x536.jpg",
          "width": 1000
        },
        "imageCaption": "オーシャンタワーの落ち着きあるツインルーム",
        "sectionTitle": "カップルから、キッズ、ワンちゃんまで、誰もが満足する客室が好評"
      },
      {
        "description": "休日をとにかくのんびり過ごしたい方も、目いっぱい遊びたい方も、出掛ける前のチェックは忘れずに。「沖縄かりゆしビーチリゾート・オーシャンスパ」では、広大な敷地内にある3つの姉妹ホテルと、白い砂浜のかりゆしビーチや散策道が整備された森などを合わせて「かりゆしワンダーランド」として紹介しています。ステイパーク、フードパーク、フォレストパーク、ワンワンパークなど、8つのテーマで紹介するリゾートライフの過ごし方はとにかく多彩です。スパ＆フィットネスパークとしては、大きなガーデンプールや、サウナ、ブロアーバスがあるラグーンパティオ、フィットネスジムなどでの心と身体を癒すリラクゼーションを提案。オーシャンタワーの露天風呂付きの大展望風呂「海の湯」とウィングタワーの「森の湯」もおすすめです。イベントパークでは、夏期を中心にさまざまなイベントを企画。プールサイドや野外ステージでのライブや特別体験プラン、冬にはイルミネーションの「かりゆしドリームファンタジー」など、いずれも心が豊かになるイベントです。マリンパークでは、シュノーケリングからパラセーリングまでさまざまなマリンレジャーやウォータープログラムを用意しています。2022年7月には敷地内にヘリポートが新設されました。那覇空港からの送迎や、遊覧飛行サービスが楽しめるようになったので、沖縄の空も存分に堪能してくださいね。次々に新しい企画やアクティビティが生まれている「沖縄かりゆしビーチリゾート・オーシャンスパ」。訪れる前にしっかりチェックをするのをおすすめします。",
        "image": {
          "alternateText": "オーシャンタワーの中庭「ラグーンパティオ」の中央には温水プールも",
          "height": 799,
          "sourceUrl": "http://a.mktgcdn.com/p/Ku2oE6dQAQiFG6_o-MsMyUnceeumrUlrx9RIAdb0ch4/1200x799.jpg",
          "thumbnails": [
            {
              "height": 799,
              "url": "//a.mktgcdn.com/p-sandbox/Ku2oE6dQAQiFG6_o-MsMyUnceeumrUlrx9RIAdb0ch4/1200x799.jpg",
              "width": 1200
            },
            {
              "height": 412,
              "url": "//a.mktgcdn.com/p-sandbox/Ku2oE6dQAQiFG6_o-MsMyUnceeumrUlrx9RIAdb0ch4/619x412.jpg",
              "width": 619
            },
            {
              "height": 400,
              "url": "//a.mktgcdn.com/p-sandbox/Ku2oE6dQAQiFG6_o-MsMyUnceeumrUlrx9RIAdb0ch4/600x400.jpg",
              "width": 600
            },
            {
              "height": 131,
              "url": "//a.mktgcdn.com/p-sandbox/Ku2oE6dQAQiFG6_o-MsMyUnceeumrUlrx9RIAdb0ch4/196x131.jpg",
              "width": 196
            }
          ],
          "url": "http://a.mktgcdn.com/p-sandbox/Ku2oE6dQAQiFG6_o-MsMyUnceeumrUlrx9RIAdb0ch4/1200x799.jpg",
          "width": 1200
        },
        "imageCaption": "オーシャンタワーの中庭「ラグーンパティオ」の中央には温水プールも",
        "sectionTitle": "“何もしない”から“空を飛ぶ”まで、「かりゆしワンダーランド」を堪能し尽くす"
      },
      {
        "description": "ホテルのホームページのメニューを検索すると「KIDS＆BABY」というメニューに目が止まります。環境省の「エコアクション21」の認証・登録を取得したホテルというだけに、環境に配慮したさまざまな取り組みをしていますが、自然に優しいホテルは人にもとても優しいのです。「KIDS＆BABY」のメニューにはそのホテルの優しさ詰まっています。赤ちゃんにはベビーベッドや補助便座などの無料貸し出しや無料の離乳食をご用意。館内には木製のおもちゃを揃えたキッズルーム「ワンダールーム」が設置され、客室タイプにはワクワクできるファミリールームがあります。コインランドリールームは2つの客室棟にそれぞれ設置。家族で楽しめるアウトドアのアクティビティもたくさんあります。グラスボートや夏期開設の「かりゆしウォーターランド」などのマリンレジャーから、かりゆしの森トレッキングやマングローブツアーなど、子ども大人も大満足です。サンゴ再生プロジェクトで企画されたサンゴの苗作り体験ができる「かりゆしビーチサンゴ教室」は貴重な体験になるのでぜひ。そして、マタニティサービスとして妊婦さんに抱き枕とマタニティ水着を用意しています。（※貸出の数に限りがあります）ゆったりと過ごすことで、おなかの赤ちゃんもママになる方も健やかに。",
        "image": {
          "alternateText": "夏期のかりゆしビーチには「かりゆしウォーターランド」が開設",
          "height": 868,
          "sourceUrl": "http://a.mktgcdn.com/p/T0PtzxlYk4jm_dCPhODFH74T5ZvHU6gRhZHrDUYEBCQ/1200x868.jpg",
          "thumbnails": [
            {
              "height": 868,
              "url": "//a.mktgcdn.com/p-sandbox/T0PtzxlYk4jm_dCPhODFH74T5ZvHU6gRhZHrDUYEBCQ/1200x868.jpg",
              "width": 1200
            },
            {
              "height": 448,
              "url": "//a.mktgcdn.com/p-sandbox/T0PtzxlYk4jm_dCPhODFH74T5ZvHU6gRhZHrDUYEBCQ/619x448.jpg",
              "width": 619
            },
            {
              "height": 434,
              "url": "//a.mktgcdn.com/p-sandbox/T0PtzxlYk4jm_dCPhODFH74T5ZvHU6gRhZHrDUYEBCQ/600x434.jpg",
              "width": 600
            },
            {
              "height": 142,
              "url": "//a.mktgcdn.com/p-sandbox/T0PtzxlYk4jm_dCPhODFH74T5ZvHU6gRhZHrDUYEBCQ/196x142.jpg",
              "width": 196
            }
          ],
          "url": "http://a.mktgcdn.com/p-sandbox/T0PtzxlYk4jm_dCPhODFH74T5ZvHU6gRhZHrDUYEBCQ/1200x868.jpg",
          "width": 1200
        },
        "imageCaption": "夏期のかりゆしビーチには「かりゆしウォーターランド」が開設",
        "sectionTitle": "マリンもランドもキッズプログラムが充実、早めのチェックで休日を満喫"
      },
      {
        "description": "このホテルには朝採れの野菜やお肉など県産食材をふんだんに取り入れた食事が楽しめるレストランと大人の時間を楽しめるバーラウンジがあります。琉球郷土料理と和・洋・中の創作ブッフェ「THE DINING 暖琉満菜」と、プールサイドで盛り上がる「BBQ ガーデン CHI」、沖縄県産和牛ややんばる島豚などを味わえる「やきにく 朝 Cho」。夏期限定でオーシャンテラスにはサンセットテラスもオープン。どのレストランの料理も絶品ですが、なかでも敷地内にある自社農園「かりゆしファーム」や地元契約農家で採れた島野菜は、みずみずしくて新鮮で生のままでも美味です。予約すれば「OKINAWA KARIYUSHI RESORT EXES ONNA」の「ダイニング 天」の利用もできます。ホテルメイドのカップデリやスイーツなどを揃えた「デリ＆カフェ」もあるので、好きなデリやスイーツを買って、好きな場所でどうぞ。エースJTBをご利用のお客様にはJTBラウンジをご用意。カフェとおいしいスイーツがサービスされ、なかでも素敵なブルーの沖縄県産バタフライピー茶はおすすめ。夕方のハッピータイムにはアルコール類のサービスもありますよ。▶\u003cspan style\u003d\"border-bottom: solid 1px blue;\"\u003e\u003ca href\u003d\"https://www.jtb.co.jp/kokunai-hotel/htl/8707006/\" target\u003d\"_blank\" rel\u003d\"noopener noreferrer\"\u003e宿の基本情報・アクセス・地図はこちら\u003c/a\u003e\u003c/span\u003e",
        "image": {
          "alternateText": "彩りも豊かに味わえる「THE DINING暖琉満菜」のディナー(イメージ)",
          "height": 800,
          "sourceUrl": "http://a.mktgcdn.com/p/04rzukEn2pLOn0VgjLQwZpP_dk_shWcB5NQ0wVDi2U4/1200x800.jpg",
          "thumbnails": [
            {
              "height": 800,
              "url": "//a.mktgcdn.com/p-sandbox/04rzukEn2pLOn0VgjLQwZpP_dk_shWcB5NQ0wVDi2U4/1200x800.jpg",
              "width": 1200
            },
            {
              "height": 413,
              "url": "//a.mktgcdn.com/p-sandbox/04rzukEn2pLOn0VgjLQwZpP_dk_shWcB5NQ0wVDi2U4/619x413.jpg",
              "width": 619
            },
            {
              "height": 400,
              "url": "//a.mktgcdn.com/p-sandbox/04rzukEn2pLOn0VgjLQwZpP_dk_shWcB5NQ0wVDi2U4/600x400.jpg",
              "width": 600
            },
            {
              "height": 131,
              "url": "//a.mktgcdn.com/p-sandbox/04rzukEn2pLOn0VgjLQwZpP_dk_shWcB5NQ0wVDi2U4/196x131.jpg",
              "width": 196
            }
          ],
          "url": "http://a.mktgcdn.com/p-sandbox/04rzukEn2pLOn0VgjLQwZpP_dk_shWcB5NQ0wVDi2U4/1200x800.jpg",
          "width": 1200
        },
        "imageCaption": "彩りも豊かに味わえる「THE DINING暖琉満菜」のディナー(イメージ)",
        "sectionTitle": "朝採れ野菜に近海魚介、地味深い島豚など、沖縄の思い出に残る料理を提供"
      },
      {
        "imageCaption": "※記事には投稿者の感性や主観が含まれます。おすすめする内容や好みには個人差がありますので何卒ご容赦ください。※記事内の情報は投稿日またはそれ以前の取材時や草稿時のものです。事後の経年変化は記事には反映できておりません。また、時期により感染症・天災等で一時的に営業状況等が変更されている場合もあります。お出かけの際は地域や施設のホームページ等で最新情報をご確認ください。"
      }
    ],
    "c_news_FeaturedArticles": [
      "news_ap_chiki_100085",
      "news_ap_chiki_100070",
      "news_ap_chiki_100073",
      "news_ap_chiki_100075",
      "news_ap_chiki_100076",
      "news_ap_chiki_100072",
      "news_ap_chiki_100074",
      "news_ap_chiki_100080",
      "news_ap_chiki_100087",
      "news_ap_chiki_100077",
      "news_ap_chiki_100083",
      "news_ap_chiki_100078",
      "news_ap_chiki_100082",
      "news_ap_chiki_100079",
      "news_ap_chiki_100081",
      "news_ap_area_000005",
      "news_ap_area_000006",
      "news_ap_area_000004",
      "news_ap_chiki_100048",
      "news_ap_chiki_100049"
    ],
    "c_news_FeaturedArticlesTitle": "沖縄県のその他の記事",
    "c_news_PublicationDate": "2022-10-26",
    "c_news_UpdateDate": "2022-10-26",
    "c_news_ViewCount": "64",
    "c_news_ViewCount1of2": "2",
    "c_news_ViewCount2of2": "64",
    "c_news_ViewCountNum": "64",
    "c_news_ViewCountNumForSorting": "5",
    "c_pagesURL": "https://www.jtb.co.jp/news/list/kokunai/okinawa/okinawa_all/news_ap_chiki_100084",
    "name": "自然にやさしい、人にやさしい、誰もが笑顔になれるリゾートホテル【沖縄県　沖縄かりゆしビーチリゾート・オーシャンスパ】",
    "slug": "kokunai/okinawa/okinawa_all/news_ap_chiki_100084",
    "timezone": "Asia/Tokyo"
  },
  "entityType": "ce_news",
  "labels": []
}