{
  "$id": "news_ap_chiki_100178",
  "$schema": "https://schema.yext.com/config/km/entity/v1",
  "primaryLocale": "ja",
  "content": {
    "c_ap_AuthorForDisplay": {
      "label": "JTB地域ナビゲーター 熊本県担当　佐田 友美"
    },
    "c_ap_HeroImage": {
      "height": 800,
      "sourceUrl": "http://a.mktgcdn.com/p/tSRUFQ43lgyMfEnXN9QfQjd_a5_WojVlFjNgT-KVlxA/1200x800.jpg",
      "thumbnails": [
        {
          "height": 800,
          "url": "//a.mktgcdn.com/p-sandbox/9Plyg9IAAos_8on8zlRoTEX2MfHW3BEQ_Vb7m09fiWk/1200x800.jpg",
          "width": 1200
        },
        {
          "height": 413,
          "url": "//a.mktgcdn.com/p-sandbox/9Plyg9IAAos_8on8zlRoTEX2MfHW3BEQ_Vb7m09fiWk/619x413.jpg",
          "width": 619
        },
        {
          "height": 400,
          "url": "//a.mktgcdn.com/p-sandbox/9Plyg9IAAos_8on8zlRoTEX2MfHW3BEQ_Vb7m09fiWk/600x400.jpg",
          "width": 600
        },
        {
          "height": 131,
          "url": "//a.mktgcdn.com/p-sandbox/9Plyg9IAAos_8on8zlRoTEX2MfHW3BEQ_Vb7m09fiWk/196x131.jpg",
          "width": 196
        }
      ],
      "url": "http://a.mktgcdn.com/p-sandbox/9Plyg9IAAos_8on8zlRoTEX2MfHW3BEQ_Vb7m09fiWk/1200x800.jpg",
      "width": 1200
    },
    "c_ap_HeroImageCaption": "客室から眺望が楽しめる25階建ての高層ホテル",
    "c_ap_LinkContents": [
      {
        "linkText": "JTBスタッフのおすすめ旅\u0026おでかけ記事一覧",
        "uRL": "https://consultants.jtb.co.jp/articles"
      },
      {
        "linkText": "リモート相談ができるトラベルコンサルタント一覧",
        "uRL": "https://consultants.jtb.co.jp/index.html"
      },
      {
        "linkText": "リモート相談の予約はこちら",
        "uRL": "https://jtb.rooms-online.jp/calendar/schedule/y-oDn-9Xw-arNbQkwVf"
      },
      {
        "linkText": "熊本旅行・ツアー・パック",
        "uRL": "https://www.jtb.co.jp/kokunai/area/kumamoto/"
      },
      {
        "linkText": "熊本県のホテル・旅館・宿",
        "uRL": "https://www.jtb.co.jp/kokunai-hotel/list/kumamoto/"
      }
    ],
    "c_ap_LinkSectionTitle": "関連リンク",
    "c_ap_PagesGeneration": true,
    "c_ap_ShortDescription": "JR熊本駅から徒歩で約8分、熊本市を流れる白川河畔に立つ「ANAクラウンプラザ熊本ニュースカイ」。周辺に高い建物がないことから、25階建ての東館上階は市街まで見渡せるほど見晴らしがよく、特に夜景は眺めているだけで心を和ませてくれます。\n客室は全187室。1〜２人旅、家族やグループ旅行に対応したスタンダードからスイートまで6タイプから選ぶことができます。なかでも、全国的に知られる地元のキャラクター「くまモン」がそこかしこにいる客室は予約するのが難しいほど大人気です。\n徒歩約5分、市内に延びる市電の停留所からは、日本三大名城の1つ「熊本城」や国の名勝・史跡に指定されている「水前寺公園」など、移動時間30分圏内の距離に観光名所があるので、市内観光の拠点として活用できます。",
    "c_ap_Tags": [
      "観光スポット",
      "朝食",
      "シティホテル",
      "眺望",
      "JTBの一押しホテル"
    ],
    "c_ap_TagsLabel": "この記事に関連するタグ",
    "c_ap_Theme": [
      "ホテル・旅館"
    ],
    "c_ap_Title": "くまモンの客室で過ごせる、ビジネス・観光に好立地のシティホテル【熊本県　ANAクラウンプラザ熊本ニュースカイ】",
    "c_linkedArea3News": [
      "oita"
    ],
    "c_metaDescription": "JR熊本駅から徒歩で約8分、熊本市を流れる白川河畔に立つ「ANAクラウンプラザ熊本ニュースカイ」。周辺に高い建物がないことから、25階建ての東館上階は市街まで見渡せるほど見晴らしがよく、特に夜景は眺めているだ…【おすすめの旅行情報はJTB】",
    "c_metaTitle": "くまモンの客室で過ごせる、ビジネス・観光に好立地のシティホテル【熊本県　ANAクラウンプラザ熊本ニュースカイ】 | JTBスタッフのおすすめ旅記事\u0026ブログ",
    "c_news_CTAs": [
      {
        "label": "ANAクラウンプラザ熊本ニュースカイを予約する",
        "link": "https://www.jtb.co.jp/kokunai-hotel/htl/8306003/plan/",
        "linkType": "URL"
      },
      {
        "label": "リモートでの旅行相談はこちら",
        "link": "https://consultants.jtb.co.jp/top#consultants",
        "linkType": "URL"
      },
      {
        "label": "JTB店舗・専門店への相談はこちら",
        "link": "https://consultants.jtb.co.jp/top#locator",
        "linkType": "OTHER"
      }
    ],
    "c_news_Contents": [
      {
        "description": "熊本を訪れたならぜひ泊まってみたいのが12階にあるくまモンデザインルームです。ぬいぐるみをはじめ、部屋のあちこちでくまモンと出会うことができますが、ベッドカバーの上にかけられたベッドスローやバスカーテン、歯ブラシケース、マグカップは「ANAクラウンプラザ熊本ニュースカイ」のオリジナルグッズ。この部屋の宿泊者には、くまモンのプチグッズとくまモンミネラルウォーターがプレゼントされる特典付きです。くまモンデザインルームを加えた客室タイプは、スタンダード、スーペリア、グランデ、プレミア、スイートの6タイプ。ダブルやツインなどのベッドの種類で分けると、セミダブル25室、ダブル12室、ツイン145室、４ベッドルーム2室、スイート3室の全187室となります。出張や1人旅ならスタンダードのセミダブルを、家族やグループ4人で泊まるなら広い空間に4つのベッドとソファが置かれたグランデを。熊本観光の拠点として、上質な空間でゆったりと過ごすなら高層階からの眺めが美しいプレミアのツインやダブル、スイートルームがおすすめです。客室へのこだわりとしてもう1つ挙げられるのが、快眠サポートプログラム。睡眠を改善するために「就寝前のリラックス」、「夜と朝のメリハリ」、「良好な睡眠環境」の3ポイントから独自に開発したもので、ピローやアロマ、加湿器などを無料で利用できます。たとえば、高さで選べるピローは、テンピュールピロー、パイプピロー、キャメルピローなど5種類とフットピローを用意。アイウォーマーで目のまわりを温めて緊張をほぐしたり、3種類から選べる天然素材のアロマでリラックスしたり、夜用のほうじ玄米茶や朝用の抹茶入ミント緑茶を就寝前と目覚めた後に飲むなど、心地よい朝を迎えるためにさまざまなサービスが提供されています。",
        "image": {
          "height": 800,
          "sourceUrl": "http://a.mktgcdn.com/p/FYE2YQSBj16zG-ZUbWqoGWKRxEbBV0zI2jGbUyrE8eI/1200x800.jpg",
          "thumbnails": [
            {
              "height": 800,
              "url": "//a.mktgcdn.com/p-sandbox/FYE2YQSBj16zG-ZUbWqoGWKRxEbBV0zI2jGbUyrE8eI/1200x800.jpg",
              "width": 1200
            },
            {
              "height": 413,
              "url": "//a.mktgcdn.com/p-sandbox/FYE2YQSBj16zG-ZUbWqoGWKRxEbBV0zI2jGbUyrE8eI/619x413.jpg",
              "width": 619
            },
            {
              "height": 400,
              "url": "//a.mktgcdn.com/p-sandbox/FYE2YQSBj16zG-ZUbWqoGWKRxEbBV0zI2jGbUyrE8eI/600x400.jpg",
              "width": 600
            },
            {
              "height": 131,
              "url": "//a.mktgcdn.com/p-sandbox/FYE2YQSBj16zG-ZUbWqoGWKRxEbBV0zI2jGbUyrE8eI/196x131.jpg",
              "width": 196
            }
          ],
          "url": "http://a.mktgcdn.com/p-sandbox/FYE2YQSBj16zG-ZUbWqoGWKRxEbBV0zI2jGbUyrE8eI/1200x800.jpg",
          "width": 1200
        },
        "imageCaption": "宿泊者限定のプレゼントが用意された、くまモンデザインルーム",
        "sectionTitle": "くまモンだけでなく、快眠にもこだわったゲストルーム"
      },
      {
        "description": "「ANAクラウンプラザ熊本ニュースカイ」には、本格的なイタリアンからオリジナル料理までが揃うレストラン「サンシエロ」、デイタイムはデザートや軽食が楽しめるバーラウンジ「フェリーチェ」、熊本の旬の食材にこだわった日本料理店「光琳」があります。寝起きの体を目覚めさせてくれる朝食は、1階のレストラン「サンシエロ」のビュッフェで。シェフが目の前で調理するオムレツやフライドエッグなどの卵料理をはじめ、和洋含めた料理の数は約80種類。パンは毎日ホテル内のパン釜で焼き上げたクロワッサンやデニッシュなど並び、香り立つできたての味が楽しめます。",
        "image": {
          "height": 799,
          "sourceUrl": "http://a.mktgcdn.com/p/rbq7EPoJjc_zVmtfvImhiKp7PL-YUM6a-DGVSZ2PjVE/1200x799.jpg",
          "thumbnails": [
            {
              "height": 799,
              "url": "//a.mktgcdn.com/p-sandbox/rbq7EPoJjc_zVmtfvImhiKp7PL-YUM6a-DGVSZ2PjVE/1200x799.jpg",
              "width": 1200
            },
            {
              "height": 412,
              "url": "//a.mktgcdn.com/p-sandbox/rbq7EPoJjc_zVmtfvImhiKp7PL-YUM6a-DGVSZ2PjVE/619x412.jpg",
              "width": 619
            },
            {
              "height": 400,
              "url": "//a.mktgcdn.com/p-sandbox/rbq7EPoJjc_zVmtfvImhiKp7PL-YUM6a-DGVSZ2PjVE/600x400.jpg",
              "width": 600
            },
            {
              "height": 131,
              "url": "//a.mktgcdn.com/p-sandbox/rbq7EPoJjc_zVmtfvImhiKp7PL-YUM6a-DGVSZ2PjVE/196x131.jpg",
              "width": 196
            }
          ],
          "url": "http://a.mktgcdn.com/p-sandbox/rbq7EPoJjc_zVmtfvImhiKp7PL-YUM6a-DGVSZ2PjVE/1200x799.jpg",
          "width": 1200
        },
        "imageCaption": "約80種類の料理から選べる朝食ビュッフェ",
        "sectionTitle": "地元の食材や郷土料理が味わえる朝食ビュッフェ＆ディナー"
      },
      {
        "description": "弾力がありあっさりとした味わいでさまざまな料理とも相性がよいと評判の熊本県産米「ひのひかり」を使った白ご飯や、有機肥料で育った八穀の古代米、郷土料理の辛子レンコンなど地元の味も並びます。「サンシエロ」はランチもビュッフェスタイルで、シェフ自慢のメイン料理から1つを選んでビュッフェをアップグレードできるチョイスワンランチブッフェも利用できます。せっかく熊本に来たのだから地元の味をもっとき楽しみたい。そんな方は日本料理店「光琳」を訪れてみましょう。ディナーはコース料理が中心ですが一品料理も充実。馬刺しの盛合せや馬スジの煮込み、馬にぎり寿司、天草産真鯛のあら炊き、あか牛の石焼きなどがおすすめです。",
        "image": {
          "height": 799,
          "sourceUrl": "http://a.mktgcdn.com/p/ES_FSvweJuwLcACK5103-S-aOLJH_eKVbMJNVTqXm_I/1200x799.jpg",
          "thumbnails": [
            {
              "height": 799,
              "url": "//a.mktgcdn.com/p-sandbox/ES_FSvweJuwLcACK5103-S-aOLJH_eKVbMJNVTqXm_I/1200x799.jpg",
              "width": 1200
            },
            {
              "height": 412,
              "url": "//a.mktgcdn.com/p-sandbox/ES_FSvweJuwLcACK5103-S-aOLJH_eKVbMJNVTqXm_I/619x412.jpg",
              "width": 619
            },
            {
              "height": 400,
              "url": "//a.mktgcdn.com/p-sandbox/ES_FSvweJuwLcACK5103-S-aOLJH_eKVbMJNVTqXm_I/600x400.jpg",
              "width": 600
            },
            {
              "height": 131,
              "url": "//a.mktgcdn.com/p-sandbox/ES_FSvweJuwLcACK5103-S-aOLJH_eKVbMJNVTqXm_I/196x131.jpg",
              "width": 196
            }
          ],
          "url": "http://a.mktgcdn.com/p-sandbox/ES_FSvweJuwLcACK5103-S-aOLJH_eKVbMJNVTqXm_I/1200x799.jpg",
          "width": 1200
        },
        "imageCaption": "熊本名産の辛子レンコンをはじめ和惣菜も数多く揃う",
        "sectionTitle": "酒屋価格でワインが味わえる「ワイン革命」とは？"
      },
      {
        "description": "「ホテルにあるレストランのワインは、値段が気になり手を出しにくい」と感じている方は、「ANAクラウンプラザ熊本ニュースカイ」のお得なサービス、ワイン革命を利用してみましょう。このサービスは、サンシエロ正面の大型ワインセラーに表示された価格でワインを注文。ホテル内のサンシエロ・光琳・フェリーチェで味わうことができます。ワインセラーには150種類以上のワインを約300本も常備。最多価格帯が1本当たり1500円〜3500円と酒屋価格なので、料理と合わせて気軽にワインを満喫できます。万一、飲み残したとしてもワインは客室に持ち帰れるので、夜景を眺めながら味わえるので安心です。ディナー後の時間にお酒を楽しみたい方は、サンシエロに併設するバーラウンジ「フェリーチェ」でワイン革命を利用したり、九州各地の焼酎を飲み比べてみたり、くつろいだひとときを過ごしてみましょう。",
        "image": {
          "height": 800,
          "sourceUrl": "http://a.mktgcdn.com/p/2NGMzn0I5cbdSdFUFHTe40dx88laBPvkIDwFBKZUU9A/1200x800.jpg",
          "thumbnails": [
            {
              "height": 800,
              "url": "//a.mktgcdn.com/p-sandbox/88deGRH1OPKRkBosBecoYkjeyrvT9yfTFZu-YdmAUnI/1200x800.jpg",
              "width": 1200
            },
            {
              "height": 413,
              "url": "//a.mktgcdn.com/p-sandbox/88deGRH1OPKRkBosBecoYkjeyrvT9yfTFZu-YdmAUnI/619x413.jpg",
              "width": 619
            },
            {
              "height": 400,
              "url": "//a.mktgcdn.com/p-sandbox/88deGRH1OPKRkBosBecoYkjeyrvT9yfTFZu-YdmAUnI/600x400.jpg",
              "width": 600
            },
            {
              "height": 131,
              "url": "//a.mktgcdn.com/p-sandbox/88deGRH1OPKRkBosBecoYkjeyrvT9yfTFZu-YdmAUnI/196x131.jpg",
              "width": 196
            }
          ],
          "url": "http://a.mktgcdn.com/p-sandbox/88deGRH1OPKRkBosBecoYkjeyrvT9yfTFZu-YdmAUnI/1200x800.jpg",
          "width": 1200
        },
        "imageCaption": "九州各地の焼酎を揃え、ワインも酒屋価格で楽しめるバーラウンジ「フェリーチェ」"
      }
    ],
    "c_news_FeaturedArticles": [
      "news_ap_h_furuta308_003",
      "news_ap_k_harada924_004",
      "news_ap_y_ishihara225_016",
      "news_ap_a_aoyama330_007",
      "news_ap_n_morita323_006",
      "news_ap_chiki_100173",
      "news_ap_m_tachibana004_005"
    ],
    "c_news_FeaturedArticlesTitle": "熊本県のその他の記事",
    "c_news_PublicationDate": "2023-09-27",
    "c_news_UpdateDate": "2023-09-27",
    "c_news_ViewCount": "25",
    "c_news_ViewCount1of2": "1",
    "c_news_ViewCount2of2": "25",
    "c_news_ViewCountNum": "25",
    "c_pagesURL": "https://www.jtb.co.jp/news/list/kokunai/kyushu/oita/news_ap_chiki_100178",
    "name": "くまモンの客室で過ごせる、ビジネス・観光に好立地のシティホテル【熊本県　ANAクラウンプラザ熊本ニュースカイ】",
    "slug": "kokunai/kyushu/oita/news_ap_chiki_100178"
  },
  "entityType": "ce_news",
  "labels": []
}