{
  "$id": "3511005588108258709",
  "$schema": "https://schema.yext.com/config/km/entity/v1",
  "primaryLocale": "ja",
  "content": {
    "c_CSS": ".Core-description {\nwhite-space: pre-wrap;\n}",
    "c_activeOnAnswers": false,
    "c_ap_ArticleCategory": "実績",
    "c_ap_AuthorForDisplay": {
      "label": "JTBリモートコンシェルジュ トラベルコンサルタント 橘 美由紀",
      "link": "https://consultants.jtb.co.jp/cp_m_tachibana004",
      "linkType": "URL"
    },
    "c_ap_Contents": [
      {
        "description": "最初に訪れたのは鎌倉市坂ノ下にある御霊神社。神社のすぐ目の前に江ノ電の線路があり、アジサイと江ノ電が一緒に鑑賞できる数少ないスポットなのだとか。でも今回は残念、タイミングが合わず江ノ電とアジサイのコラボ写真は撮れませんでした（泣）",
        "image": {
          "height": 629,
          "sourceUrl": "https://a.mktgcdn.com/p/7M9GYHtHiL41JLnxHdjqIEWKLQ557F3gTrdc5mNDqm4/979x629.jpg",
          "thumbnails": [
            {
              "height": 629,
              "url": "https://a.mktgcdn.com/p-sandbox/7M9GYHtHiL41JLnxHdjqIEWKLQ557F3gTrdc5mNDqm4/979x629.jpg",
              "width": 979
            },
            {
              "height": 398,
              "url": "https://a.mktgcdn.com/p-sandbox/7M9GYHtHiL41JLnxHdjqIEWKLQ557F3gTrdc5mNDqm4/619x398.jpg",
              "width": 619
            },
            {
              "height": 385,
              "url": "https://a.mktgcdn.com/p-sandbox/7M9GYHtHiL41JLnxHdjqIEWKLQ557F3gTrdc5mNDqm4/600x385.jpg",
              "width": 600
            },
            {
              "height": 126,
              "url": "https://a.mktgcdn.com/p-sandbox/7M9GYHtHiL41JLnxHdjqIEWKLQ557F3gTrdc5mNDqm4/196x126.jpg",
              "width": 196
            }
          ],
          "url": "https://a.mktgcdn.com/p-sandbox/7M9GYHtHiL41JLnxHdjqIEWKLQ557F3gTrdc5mNDqm4/979x629.jpg",
          "width": 979
        }
      },
      {
        "description": "気を取り直して境内の甘味処で休憩",
        "image": {
          "height": 633,
          "sourceUrl": "https://a.mktgcdn.com/p/KgtJS9KkEbe9r8wuylFuB6y6DFADDfrGdoXLq8k3L4c/994x633.jpg",
          "thumbnails": [
            {
              "height": 633,
              "url": "https://a.mktgcdn.com/p-sandbox/KgtJS9KkEbe9r8wuylFuB6y6DFADDfrGdoXLq8k3L4c/994x633.jpg",
              "width": 994
            },
            {
              "height": 394,
              "url": "https://a.mktgcdn.com/p-sandbox/KgtJS9KkEbe9r8wuylFuB6y6DFADDfrGdoXLq8k3L4c/619x394.jpg",
              "width": 619
            },
            {
              "height": 382,
              "url": "https://a.mktgcdn.com/p-sandbox/KgtJS9KkEbe9r8wuylFuB6y6DFADDfrGdoXLq8k3L4c/600x382.jpg",
              "width": 600
            },
            {
              "height": 125,
              "url": "https://a.mktgcdn.com/p-sandbox/KgtJS9KkEbe9r8wuylFuB6y6DFADDfrGdoXLq8k3L4c/196x125.jpg",
              "width": 196
            }
          ],
          "url": "https://a.mktgcdn.com/p-sandbox/KgtJS9KkEbe9r8wuylFuB6y6DFADDfrGdoXLq8k3L4c/994x633.jpg",
          "width": 994
        }
      },
      {
        "description": "途中で見つけたアンティーク調の雑貨屋さん。でも今日は弾丸旅。買いたい衝動を抑えて次のスポットへ",
        "image": {
          "height": 449,
          "sourceUrl": "https://a.mktgcdn.com/p/V3JweJqTft179Xu9im0gfM0x879m-2S-YkdT0UPusyk/990x449.jpg",
          "thumbnails": [
            {
              "height": 449,
              "url": "https://a.mktgcdn.com/p-sandbox/V3JweJqTft179Xu9im0gfM0x879m-2S-YkdT0UPusyk/990x449.jpg",
              "width": 990
            },
            {
              "height": 281,
              "url": "https://a.mktgcdn.com/p-sandbox/V3JweJqTft179Xu9im0gfM0x879m-2S-YkdT0UPusyk/619x281.jpg",
              "width": 619
            },
            {
              "height": 272,
              "url": "https://a.mktgcdn.com/p-sandbox/V3JweJqTft179Xu9im0gfM0x879m-2S-YkdT0UPusyk/600x272.jpg",
              "width": 600
            },
            {
              "height": 89,
              "url": "https://a.mktgcdn.com/p-sandbox/V3JweJqTft179Xu9im0gfM0x879m-2S-YkdT0UPusyk/196x89.jpg",
              "width": 196
            }
          ],
          "url": "https://a.mktgcdn.com/p-sandbox/V3JweJqTft179Xu9im0gfM0x879m-2S-YkdT0UPusyk/990x449.jpg",
          "width": 990
        }
      },
      {
        "description": "やってきました、鎌倉といえばここ長谷寺です",
        "image": {
          "height": 615,
          "sourceUrl": "https://a.mktgcdn.com/p/QvxcLV7NDHs8uXB1XmIDtiR9mWtYHd0jijl4dmRtNGI/988x615.jpg",
          "thumbnails": [
            {
              "height": 615,
              "url": "https://a.mktgcdn.com/p-sandbox/QvxcLV7NDHs8uXB1XmIDtiR9mWtYHd0jijl4dmRtNGI/988x615.jpg",
              "width": 988
            },
            {
              "height": 385,
              "url": "https://a.mktgcdn.com/p-sandbox/QvxcLV7NDHs8uXB1XmIDtiR9mWtYHd0jijl4dmRtNGI/619x385.jpg",
              "width": 619
            },
            {
              "height": 373,
              "url": "https://a.mktgcdn.com/p-sandbox/QvxcLV7NDHs8uXB1XmIDtiR9mWtYHd0jijl4dmRtNGI/600x373.jpg",
              "width": 600
            },
            {
              "height": 122,
              "url": "https://a.mktgcdn.com/p-sandbox/QvxcLV7NDHs8uXB1XmIDtiR9mWtYHd0jijl4dmRtNGI/196x122.jpg",
              "width": 196
            }
          ],
          "url": "https://a.mktgcdn.com/p-sandbox/QvxcLV7NDHs8uXB1XmIDtiR9mWtYHd0jijl4dmRtNGI/988x615.jpg",
          "width": 988
        }
      },
      {
        "description": "きれいに撮れました！見てください、このアジサイ。やっぱり絵になります",
        "image": {
          "height": 644,
          "sourceUrl": "https://a.mktgcdn.com/p/XwycaCHxW_MAgT_eqbiE8eKHWP4iH-lNllIhUEEaNvM/985x644.jpg",
          "thumbnails": [
            {
              "height": 644,
              "url": "https://a.mktgcdn.com/p-sandbox/XwycaCHxW_MAgT_eqbiE8eKHWP4iH-lNllIhUEEaNvM/985x644.jpg",
              "width": 985
            },
            {
              "height": 405,
              "url": "https://a.mktgcdn.com/p-sandbox/XwycaCHxW_MAgT_eqbiE8eKHWP4iH-lNllIhUEEaNvM/619x405.jpg",
              "width": 619
            },
            {
              "height": 392,
              "url": "https://a.mktgcdn.com/p-sandbox/XwycaCHxW_MAgT_eqbiE8eKHWP4iH-lNllIhUEEaNvM/600x392.jpg",
              "width": 600
            },
            {
              "height": 128,
              "url": "https://a.mktgcdn.com/p-sandbox/XwycaCHxW_MAgT_eqbiE8eKHWP4iH-lNllIhUEEaNvM/196x128.jpg",
              "width": 196
            }
          ],
          "url": "https://a.mktgcdn.com/p-sandbox/XwycaCHxW_MAgT_eqbiE8eKHWP4iH-lNllIhUEEaNvM/985x644.jpg",
          "width": 985
        }
      },
      {
        "description": "お寺をはしごしたあとは、海のほうへ。由比ガ浜にある「苔むすび」というアトリエ兼ショップを見つけました。ご主人は苔の研究家で、ここにあった古民家を改築してアトリエにしたのだとか。店内には、透明な容器の中で苔を育てる“苔テラリウム”がいっぱいです。",
        "image": {
          "height": 672,
          "sourceUrl": "https://a.mktgcdn.com/p/ImT8SZk-m95Si63FWJBdih308pQAWo6OjKMM9DEyxBI/996x672.jpg",
          "thumbnails": [
            {
              "height": 672,
              "url": "https://a.mktgcdn.com/p-sandbox/ImT8SZk-m95Si63FWJBdih308pQAWo6OjKMM9DEyxBI/996x672.jpg",
              "width": 996
            },
            {
              "height": 418,
              "url": "https://a.mktgcdn.com/p-sandbox/ImT8SZk-m95Si63FWJBdih308pQAWo6OjKMM9DEyxBI/619x418.jpg",
              "width": 619
            },
            {
              "height": 405,
              "url": "https://a.mktgcdn.com/p-sandbox/ImT8SZk-m95Si63FWJBdih308pQAWo6OjKMM9DEyxBI/600x405.jpg",
              "width": 600
            },
            {
              "height": 132,
              "url": "https://a.mktgcdn.com/p-sandbox/ImT8SZk-m95Si63FWJBdih308pQAWo6OjKMM9DEyxBI/196x132.jpg",
              "width": 196
            }
          ],
          "url": "https://a.mktgcdn.com/p-sandbox/ImT8SZk-m95Si63FWJBdih308pQAWo6OjKMM9DEyxBI/996x672.jpg",
          "width": 996
        }
      },
      {
        "description": "せっかくなので由比ガ浜をぶらりお散歩。晴れ渡る初夏の空と海。やっぱり来てよかった",
        "image": {
          "height": 555,
          "sourceUrl": "https://a.mktgcdn.com/p/28aL2rhmvDxN4xC_4lIzOOrf8KwgAdPRwNvQNIKxTAA/986x555.jpg",
          "thumbnails": [
            {
              "height": 555,
              "url": "https://a.mktgcdn.com/p-sandbox/28aL2rhmvDxN4xC_4lIzOOrf8KwgAdPRwNvQNIKxTAA/986x555.jpg",
              "width": 986
            },
            {
              "height": 348,
              "url": "https://a.mktgcdn.com/p-sandbox/28aL2rhmvDxN4xC_4lIzOOrf8KwgAdPRwNvQNIKxTAA/619x348.jpg",
              "width": 619
            },
            {
              "height": 338,
              "url": "https://a.mktgcdn.com/p-sandbox/28aL2rhmvDxN4xC_4lIzOOrf8KwgAdPRwNvQNIKxTAA/600x338.jpg",
              "width": 600
            },
            {
              "height": 110,
              "url": "https://a.mktgcdn.com/p-sandbox/28aL2rhmvDxN4xC_4lIzOOrf8KwgAdPRwNvQNIKxTAA/196x110.jpg",
              "width": 196
            }
          ],
          "url": "https://a.mktgcdn.com/p-sandbox/28aL2rhmvDxN4xC_4lIzOOrf8KwgAdPRwNvQNIKxTAA/986x555.jpg",
          "width": 986
        }
      },
      {
        "description": "そろそろお腹が空いてきました。ここに行こうね、と前もって調べていたビストロ「ouioui（ウィウィ）」へ。ここはもともと鎌倉駅にあったお店ですが、今年の4月に長谷に移転・ニューオープンしたのだそう。ホワイトが基調のかわいらしくて落ち着く雰囲気です",
        "image": {
          "height": 611,
          "sourceUrl": "https://a.mktgcdn.com/p/kXNF2SywY4QMpCyJcrcHilriWE3bXHDnR3H2D2SrkPs/928x611.jpg",
          "thumbnails": [
            {
              "height": 611,
              "url": "https://a.mktgcdn.com/p-sandbox/kXNF2SywY4QMpCyJcrcHilriWE3bXHDnR3H2D2SrkPs/928x611.jpg",
              "width": 928
            },
            {
              "height": 408,
              "url": "https://a.mktgcdn.com/p-sandbox/kXNF2SywY4QMpCyJcrcHilriWE3bXHDnR3H2D2SrkPs/619x408.jpg",
              "width": 619
            },
            {
              "height": 395,
              "url": "https://a.mktgcdn.com/p-sandbox/kXNF2SywY4QMpCyJcrcHilriWE3bXHDnR3H2D2SrkPs/600x395.jpg",
              "width": 600
            },
            {
              "height": 129,
              "url": "https://a.mktgcdn.com/p-sandbox/kXNF2SywY4QMpCyJcrcHilriWE3bXHDnR3H2D2SrkPs/196x129.jpg",
              "width": 196
            }
          ],
          "url": "https://a.mktgcdn.com/p-sandbox/kXNF2SywY4QMpCyJcrcHilriWE3bXHDnR3H2D2SrkPs/928x611.jpg",
          "width": 928
        }
      },
      {
        "description": "オーダーしたのは「魚介の盛り合わせ」。海老・イカ・帆立・ムール貝の冷製蒸しにアンチョビソース＆バジルソースを付けていただく、贅沢な逸品です。フランスではベーシックなメニューなのだそう。魚介の旨味を増倍させるオリジナルのソースがおいしすぎて、さわやかな海を感じられました",
        "image": {
          "height": 615,
          "sourceUrl": "https://a.mktgcdn.com/p/rfAT__Ki2R6ljBYGX38-jV6GRNHPkZLZlxwQZscpxB4/935x615.jpg",
          "thumbnails": [
            {
              "height": 615,
              "url": "https://a.mktgcdn.com/p-sandbox/rfAT__Ki2R6ljBYGX38-jV6GRNHPkZLZlxwQZscpxB4/935x615.jpg",
              "width": 935
            },
            {
              "height": 407,
              "url": "https://a.mktgcdn.com/p-sandbox/rfAT__Ki2R6ljBYGX38-jV6GRNHPkZLZlxwQZscpxB4/619x407.jpg",
              "width": 619
            },
            {
              "height": 395,
              "url": "https://a.mktgcdn.com/p-sandbox/rfAT__Ki2R6ljBYGX38-jV6GRNHPkZLZlxwQZscpxB4/600x395.jpg",
              "width": 600
            },
            {
              "height": 129,
              "url": "https://a.mktgcdn.com/p-sandbox/rfAT__Ki2R6ljBYGX38-jV6GRNHPkZLZlxwQZscpxB4/196x129.jpg",
              "width": 196
            }
          ],
          "url": "https://a.mktgcdn.com/p-sandbox/rfAT__Ki2R6ljBYGX38-jV6GRNHPkZLZlxwQZscpxB4/935x615.jpg",
          "width": 935
        }
      },
      {
        "description": "旅といえばこちらも欠かせません。スタッフさんにおすすめしてもらった白ワインと、クラフトビールで乾杯。大満足です",
        "image": {
          "height": 591,
          "sourceUrl": "https://a.mktgcdn.com/p/eINjWDsACfwoqbMmZvlE1YQGbM_s6TEE940Xxrqy5i0/937x591.jpg",
          "thumbnails": [
            {
              "height": 591,
              "url": "https://a.mktgcdn.com/p-sandbox/eINjWDsACfwoqbMmZvlE1YQGbM_s6TEE940Xxrqy5i0/937x591.jpg",
              "width": 937
            },
            {
              "height": 390,
              "url": "https://a.mktgcdn.com/p-sandbox/eINjWDsACfwoqbMmZvlE1YQGbM_s6TEE940Xxrqy5i0/619x390.jpg",
              "width": 619
            },
            {
              "height": 378,
              "url": "https://a.mktgcdn.com/p-sandbox/eINjWDsACfwoqbMmZvlE1YQGbM_s6TEE940Xxrqy5i0/600x378.jpg",
              "width": 600
            },
            {
              "height": 124,
              "url": "https://a.mktgcdn.com/p-sandbox/eINjWDsACfwoqbMmZvlE1YQGbM_s6TEE940Xxrqy5i0/196x124.jpg",
              "width": 196
            }
          ],
          "url": "https://a.mktgcdn.com/p-sandbox/eINjWDsACfwoqbMmZvlE1YQGbM_s6TEE940Xxrqy5i0/937x591.jpg",
          "width": 937
        }
      },
      {
        "description": "本日ラストは、こちらの旅館。といっても泊まるわけではなくて、お風呂とサウナにやってきました。",
        "image": {
          "height": 492,
          "sourceUrl": "https://a.mktgcdn.com/p/lcP00hNRXj_nUIVZsniSKRFgjKEZ2Ouk-B8Zj2eJaJA/939x492.jpg",
          "thumbnails": [
            {
              "height": 492,
              "url": "https://a.mktgcdn.com/p-sandbox/lcP00hNRXj_nUIVZsniSKRFgjKEZ2Ouk-B8Zj2eJaJA/939x492.jpg",
              "width": 939
            },
            {
              "height": 324,
              "url": "https://a.mktgcdn.com/p-sandbox/lcP00hNRXj_nUIVZsniSKRFgjKEZ2Ouk-B8Zj2eJaJA/619x324.jpg",
              "width": 619
            },
            {
              "height": 314,
              "url": "https://a.mktgcdn.com/p-sandbox/lcP00hNRXj_nUIVZsniSKRFgjKEZ2Ouk-B8Zj2eJaJA/600x314.jpg",
              "width": 600
            },
            {
              "height": 103,
              "url": "https://a.mktgcdn.com/p-sandbox/lcP00hNRXj_nUIVZsniSKRFgjKEZ2Ouk-B8Zj2eJaJA/196x103.jpg",
              "width": 196
            }
          ],
          "url": "https://a.mktgcdn.com/p-sandbox/lcP00hNRXj_nUIVZsniSKRFgjKEZ2Ouk-B8Zj2eJaJA/939x492.jpg",
          "width": 939
        }
      },
      {
        "description": "落ち着く館内。一日の疲れが癒されます",
        "image": {
          "height": 720,
          "sourceUrl": "https://a.mktgcdn.com/p/ckBD1x6vptb7Erty5mmkkQudsT9wZZnONk5nlSbJBHE/972x720.jpg",
          "thumbnails": [
            {
              "height": 720,
              "url": "https://a.mktgcdn.com/p-sandbox/ckBD1x6vptb7Erty5mmkkQudsT9wZZnONk5nlSbJBHE/972x720.jpg",
              "width": 972
            },
            {
              "height": 459,
              "url": "https://a.mktgcdn.com/p-sandbox/ckBD1x6vptb7Erty5mmkkQudsT9wZZnONk5nlSbJBHE/619x459.jpg",
              "width": 619
            },
            {
              "height": 444,
              "url": "https://a.mktgcdn.com/p-sandbox/ckBD1x6vptb7Erty5mmkkQudsT9wZZnONk5nlSbJBHE/600x444.jpg",
              "width": 600
            },
            {
              "height": 145,
              "url": "https://a.mktgcdn.com/p-sandbox/ckBD1x6vptb7Erty5mmkkQudsT9wZZnONk5nlSbJBHE/196x145.jpg",
              "width": 196
            }
          ],
          "url": "https://a.mktgcdn.com/p-sandbox/ckBD1x6vptb7Erty5mmkkQudsT9wZZnONk5nlSbJBHE/972x720.jpg",
          "width": 972
        }
      },
      {
        "description": "こちらはおみやげです。鎌倉の夏を彩るカラフルでみずみずしい旬粋ゼリー各270円。帰り際、JR鎌倉駅の駅ビルCIAL（シァル）の1階にある「鎌倉旬粋」でゲットしました。気軽に立ち寄れる雰囲気のセレクトショップ。ここでしか手に入らないオリジナル商品も取り揃えていました。さわやかな夏を感じられますね",
        "image": {
          "height": 475,
          "sourceUrl": "https://a.mktgcdn.com/p/sK4wRoxqNIbN-o7y9rl3R6NP_pPpr1J13TMLRlpYBHs/990x475.jpg",
          "thumbnails": [
            {
              "height": 475,
              "url": "https://a.mktgcdn.com/p-sandbox/sK4wRoxqNIbN-o7y9rl3R6NP_pPpr1J13TMLRlpYBHs/990x475.jpg",
              "width": 990
            },
            {
              "height": 297,
              "url": "https://a.mktgcdn.com/p-sandbox/sK4wRoxqNIbN-o7y9rl3R6NP_pPpr1J13TMLRlpYBHs/619x297.jpg",
              "width": 619
            },
            {
              "height": 288,
              "url": "https://a.mktgcdn.com/p-sandbox/sK4wRoxqNIbN-o7y9rl3R6NP_pPpr1J13TMLRlpYBHs/600x288.jpg",
              "width": 600
            },
            {
              "height": 94,
              "url": "https://a.mktgcdn.com/p-sandbox/sK4wRoxqNIbN-o7y9rl3R6NP_pPpr1J13TMLRlpYBHs/196x94.jpg",
              "width": 196
            }
          ],
          "url": "https://a.mktgcdn.com/p-sandbox/sK4wRoxqNIbN-o7y9rl3R6NP_pPpr1J13TMLRlpYBHs/990x475.jpg",
          "width": 990
        }
      },
      {
        "description": "最初に訪れた御霊神社の御朱印。ここにもアジサイがあるのですね。",
        "image": {
          "height": 642,
          "sourceUrl": "https://a.mktgcdn.com/p/6cm1hsBq4B_uOZCH42xfaeDyk0lphnMxROM_yEBxoDs/990x642.jpg",
          "thumbnails": [
            {
              "height": 642,
              "url": "https://a.mktgcdn.com/p-sandbox/6cm1hsBq4B_uOZCH42xfaeDyk0lphnMxROM_yEBxoDs/990x642.jpg",
              "width": 990
            },
            {
              "height": 401,
              "url": "https://a.mktgcdn.com/p-sandbox/6cm1hsBq4B_uOZCH42xfaeDyk0lphnMxROM_yEBxoDs/619x401.jpg",
              "width": 619
            },
            {
              "height": 389,
              "url": "https://a.mktgcdn.com/p-sandbox/6cm1hsBq4B_uOZCH42xfaeDyk0lphnMxROM_yEBxoDs/600x389.jpg",
              "width": 600
            },
            {
              "height": 127,
              "url": "https://a.mktgcdn.com/p-sandbox/6cm1hsBq4B_uOZCH42xfaeDyk0lphnMxROM_yEBxoDs/196x127.jpg",
              "width": 196
            }
          ],
          "url": "https://a.mktgcdn.com/p-sandbox/6cm1hsBq4B_uOZCH42xfaeDyk0lphnMxROM_yEBxoDs/990x642.jpg",
          "width": 990
        }
      },
      {
        "description": "日帰り弾丸でしたが、大充実の鎌倉旅でした！この季節、やっぱりおすすめです。また行きたいな。"
      }
    ],
    "c_ap_DatePosted": "2022-06-04",
    "c_ap_HeroImage": {
      "height": 582,
      "sourceUrl": "https://a.mktgcdn.com/p/Yzdb74HYQTXPgZYRilwkRbGoS9DEJrcu0wkEMvQZ3io/977x582.jpg",
      "thumbnails": [
        {
          "height": 582,
          "url": "https://a.mktgcdn.com/p-sandbox/Yzdb74HYQTXPgZYRilwkRbGoS9DEJrcu0wkEMvQZ3io/977x582.jpg",
          "width": 977
        },
        {
          "height": 369,
          "url": "https://a.mktgcdn.com/p-sandbox/Yzdb74HYQTXPgZYRilwkRbGoS9DEJrcu0wkEMvQZ3io/619x369.jpg",
          "width": 619
        },
        {
          "height": 357,
          "url": "https://a.mktgcdn.com/p-sandbox/Yzdb74HYQTXPgZYRilwkRbGoS9DEJrcu0wkEMvQZ3io/600x357.jpg",
          "width": 600
        },
        {
          "height": 117,
          "url": "https://a.mktgcdn.com/p-sandbox/Yzdb74HYQTXPgZYRilwkRbGoS9DEJrcu0wkEMvQZ3io/196x117.jpg",
          "width": 196
        }
      ],
      "url": "https://a.mktgcdn.com/p-sandbox/Yzdb74HYQTXPgZYRilwkRbGoS9DEJrcu0wkEMvQZ3io/977x582.jpg",
      "width": 977
    },
    "c_ap_LinkContents": [
      {
        "linkText": "橘 美由紀 のリモート相談予約はこちらまで",
        "uRL": "https://link.rooms-online.jp/calendar/schedule/y-oDn-9Xw-arNF1DN-qJBbQ7"
      },
      {
        "linkText": "リモート相談ができるトラベルコンサルタント一覧",
        "uRL": "https://consultants.jtb.co.jp/index.html"
      },
      {
        "linkText": "JTBスタッフのおすすめ旅\u0026おでかけ記事一覧",
        "uRL": "https://consultants.jtb.co.jp/articles"
      },
      {
        "linkText": "鎌倉・湘南のホテル・旅館・宿",
        "uRL": "https://www.jtb.co.jp/kokunai-hotel/list/1403/"
      }
    ],
    "c_ap_LinkSectionTitle": "LINKS",
    "c_ap_RelatedLocalArea2": [
      "神奈川県"
    ],
    "c_ap_ShortDescription": "梅雨入り前、6月最初の休日。\n鎌倉に行きたいと言っていた親友とぴったり休みが重なったので、大阪から日帰り弾丸ツアーに行ってきました！\nこれからの季節、寺社や公園にアジサイの花々が咲き誇ります。私の一眼レフで収めた鎌倉の初夏をご紹介します！",
    "c_ap_Tags": [
      "初夏",
      "鎌倉",
      "アジサイ"
    ],
    "c_ap_Title": "初夏のアジサイシーズン到来！鎌倉に行ってきました～♪",
    "c_cSSMobile": ".Core-description {\nwhite-space: pre-wrap;\n}",
    "c_metaDescription": "梅雨入り前、6月最初の休日。\n鎌倉に行きたいと言っていた親友とぴったり休みが重なったので、大阪から日帰り弾丸ツアーに行ってきました！\nこれからの季節、寺社や公園にアジサイの花々が咲き誇ります。私の一眼レフで収めた鎌倉の初夏をご紹介します！",
    "c_metaTitle": "JTB | スタッフ | おすすめ | 旅 | 記事 | ブログ |初夏のアジサイシーズン到来！鎌倉に行ってきました～♪",
    "c_searchArea1": [
      "国内"
    ],
    "c_searchArea2": "神奈川県",
    "c_searchTags": [
      "中部・北陸：",
      "近畿：",
      "中国・四国：",
      "九州・沖縄：",
      "太平洋・オセアニア：",
      "北米・中南米：",
      "ヨーロッパ：",
      "アジア：",
      "アフリカ・中近東：",
      "海外６：",
      "海外７："
    ],
    "keywords": [
      "中部・北陸：",
      "近畿：",
      "中国・四国：",
      "九州・沖縄：",
      "太平洋・オセアニア：",
      "北米・中南米：",
      "ヨーロッパ：",
      "アジア：",
      "アフリカ・中近東：",
      "海外６：",
      "海外７："
    ],
    "name": "ブログサンプル2",
    "timezone": "Asia/Tokyo"
  },
  "entityType": "ce_article",
  "folder": "299648",
  "labels": []
}