{
  "$id": "JDPSN0001A",
  "$schema": "https://schema.yext.com/config/km/entity/v1",
  "primaryLocale": "ja",
  "content": {
    "c_activeOnAnswers": true,
    "c_ap_PagesGeneration": true,
    "c_imageURL": "https://column.jtb.co.jp/KCMSImage/15b13e9d-e207-4a54-9c1b-1a70a596905e.jpg",
    "c_searchArea1": [
      "海外"
    ],
    "c_searchArea2": "インドネシア",
    "description": "青い海、青い空、トロピカルガーデンに囲まれての挙式に写真撮影。\nプール付きヴィラでゆっくり滞在しながらも旅の後半はバリ島観光へ。\n\n宿泊は、ホテル内に挙式チャペルがある「アヤナ ヴィラズ バリ」。\nリゾート内には「JTBラウンジ」もあるので安心してお過ごしいただけます。\n\n※2023年8月現在の情報です。\n※バリ島ウエディングはWEBでのお申込みを受付しておりません。JTB取り扱い店舗へご相談ください。",
    "keywords": [
      "アジア",
      "インドネシア",
      "デンパサール(バリ島)",
      "ウエディング"
    ],
    "landingPageUrl": "https://column.jtb.co.jp/plan/AJQ07/JDPSN0001A/",
    "name": "青い海を目の前に、憧れリゾートでプレミアムなウエディングを叶えるバリ島ウエディング【アヤナ リゾート バリ　トゥリスナ】4泊6日"
  },
  "entityType": "ce_article2",
  "folder": "海外おすすめプラン特集",
  "labels": []
}