{
  "$id": "cp_10232039",
  "$schema": "https://schema.yext.com/config/km/entity/v1",
  "primaryLocale": "ja",
  "content": {
    "c_CSS": ".Core-description {\nwhite-space: pre-wrap;\n}",
    "c_cSSMobile": ".Core-description {\nwhite-space: pre-wrap;\n}",
    "c_cp_BranchOfficeRegion": "兵庫県",
    "c_cp_CTA1": {
      "label": "西尾 の相談予約はこちら",
      "link": "https://jtb.rooms-online.jp/calendar/schedule/y-oDn-9Xw-arNbQgwVB9xKX",
      "linkType": "URL"
    },
    "c_cp_CTA2": {
      "label": "このコンサルタントがいる店舗の相談予約はこちら",
      "link": "https://jtb.rooms-online.jp/calendar/schedule/y-oDn-9Xw-arNbQkwVBrxd",
      "linkType": "URL"
    },
    "c_cp_Description": "笑顔で楽しくお話させて頂きたいと思っています！まだまだ勉強中ではございますが、お客様のご希望に応えられるよう、精一杯頑張ります！海沿いのドライブや、テーマパーク、ライブへ行くことが大好きです。",
    "c_cp_DisplayName": "西尾",
    "c_cp_FieldOfExpertise": [
      "テーマパーク",
      "音楽ライブ"
    ],
    "c_cp_HiraganaName": "にしお",
    "c_cp_JobTitle": "JTB西宮北口店 トラベルコンサルタント",
    "c_cp_OverseasExpert": {
      "area1": {
        "rank": "bronze"
      }
    },
    "c_cp_PagesGeneration": true,
    "c_cp_Photo": {
      "height": 1255,
      "sourceUrl": "https://a.mktgcdn.com/p/4FKfjaOSXYzNjRTT33TBCwvS6RPmq4t_Y7mT2WW-IGA/1108x1255.jpg",
      "thumbnails": [
        {
          "height": 1255,
          "url": "https://a.mktgcdn.com/p-sandbox/tqR_ekJneCHkmmeA7wEm-htiiWokr9lkOrnTpli49ac/1108x1255.jpg",
          "width": 1108
        },
        {
          "height": 701,
          "url": "https://a.mktgcdn.com/p-sandbox/tqR_ekJneCHkmmeA7wEm-htiiWokr9lkOrnTpli49ac/619x701.jpg",
          "width": 619
        },
        {
          "height": 450,
          "url": "https://a.mktgcdn.com/p-sandbox/tqR_ekJneCHkmmeA7wEm-htiiWokr9lkOrnTpli49ac/397x450.jpg",
          "width": 397
        },
        {
          "height": 222,
          "url": "https://a.mktgcdn.com/p-sandbox/tqR_ekJneCHkmmeA7wEm-htiiWokr9lkOrnTpli49ac/196x222.jpg",
          "width": 196
        }
      ],
      "url": "https://a.mktgcdn.com/p-sandbox/tqR_ekJneCHkmmeA7wEm-htiiWokr9lkOrnTpli49ac/1108x1255.jpg",
      "width": 1108
    },
    "c_cp_StrongAbroadArea1": [
      "ハワイ"
    ],
    "c_cp_StrongAbroadArea4": [
      "韓国"
    ],
    "c_cp_StrongLocalArea2": [
      "千葉県",
      "東京都"
    ],
    "c_cp_StrongLocalArea4": [
      "兵庫県"
    ],
    "c_cp_Tags": [
      "【こちらの方面なら特にお任せください！】アジア・韓国・ハワイ",
      "2024年6月にハワイへ行ってきました！",
      "テーマパーク・女子旅",
      "母娘旅",
      "ハワイ上級スペシャリスト"
    ],
    "c_metaDescription": "JTBトラベルコンサルタント | 西尾 萌絵果",
    "c_metaTitle": "JTBトラベルコンサルタント | 西尾 萌絵果",
    "c_pagesURL": "https://consultants.jtb.co.jp/cp_10232039",
    "c_responsibleService": [
      "リテール店舗"
    ],
    "c_v2Folder": "10343_西宮北口店",
    "name": "にしお_10232039",
    "timezone": "Asia/Tokyo"
  },
  "entityType": "ce_consultant",
  "labels": []
}