{
  "$id": "cp_20051320",
  "$schema": "https://schema.yext.com/config/km/entity/v1",
  "primaryLocale": "ja",
  "content": {
    "c_CSS": ".Core-description {\nwhite-space: pre-wrap;\n}",
    "c_cSSMobile": ".Core-description {\nwhite-space: pre-wrap;\n}",
    "c_cp_BranchOfficeRegion": "静岡県",
    "c_cp_CTA1": {
      "label": "堀田 の海外相談予約はこちら",
      "link": "https://jtb.rooms-online.jp/calendar/schedule/y-oDn-9Xw-arNbQgwVfgxVB",
      "linkType": "URL"
    },
    "c_cp_CTA2": {
      "label": "このコンサルタントがいる店舗の相談予約はこちら",
      "link": "https://jtb.rooms-online.jp/calendar/schedule/y-oDn-9Xw-arNbQkwVer_q",
      "linkType": "URL"
    },
    "c_cp_Description": "\u003cfont color\u003d\"red\"\u003eお話をじっくり聞いて、楽しいご提案を心がけています\u003c/font\u003e\n\n●ご挨拶：私の旅の楽しみ方\n旅マエ―どんな映えスポットがあるか徹底調査\n旅ナカ－写真撮影に夢中\n旅アト－思い出アルバムを作成旅行は人それぞれいろい\nろな楽しみ方があると思います。旅行に行く前か\nら帰ってくるまでの楽しい思い出作りをさせてい\nただいたら嬉しいです",
    "c_cp_DisplayName": "堀田",
    "c_cp_GeneralInfo": [
      "●資格：総合旅行業務取扱管理者・トラベルコーディネーター国内海外A級・アロハプログラム上級"
    ],
    "c_cp_JobTitle": "JTBマークイズ静岡店　トラベルコンサルタント",
    "c_cp_PagesGeneration": true,
    "c_cp_Photo": {
      "height": 3275,
      "sourceUrl": "https://a.mktgcdn.com/p/6wvH9wvv8abNGtkpkyd-wS681e5pJz3b4eBtXKgKYHA/2510x3275.jpg",
      "thumbnails": [
        {
          "height": 3275,
          "url": "https://a.mktgcdn.com/p-sandbox/6wvH9wvv8abNGtkpkyd-wS681e5pJz3b4eBtXKgKYHA/2510x3275.jpg",
          "width": 2510
        },
        {
          "height": 1900,
          "url": "https://a.mktgcdn.com/p-sandbox/6wvH9wvv8abNGtkpkyd-wS681e5pJz3b4eBtXKgKYHA/1456x1900.jpg",
          "width": 1456
        },
        {
          "height": 808,
          "url": "https://a.mktgcdn.com/p-sandbox/6wvH9wvv8abNGtkpkyd-wS681e5pJz3b4eBtXKgKYHA/619x808.jpg",
          "width": 619
        },
        {
          "height": 450,
          "url": "https://a.mktgcdn.com/p-sandbox/6wvH9wvv8abNGtkpkyd-wS681e5pJz3b4eBtXKgKYHA/345x450.jpg",
          "width": 345
        },
        {
          "height": 256,
          "url": "https://a.mktgcdn.com/p-sandbox/6wvH9wvv8abNGtkpkyd-wS681e5pJz3b4eBtXKgKYHA/196x256.jpg",
          "width": 196
        }
      ],
      "url": "https://a.mktgcdn.com/p-sandbox/6wvH9wvv8abNGtkpkyd-wS681e5pJz3b4eBtXKgKYHA/2510x3275.jpg",
      "width": 2510
    },
    "c_cp_Point": "1229",
    "c_cp_StrongAbroadArea4": [
      "シンガポール"
    ],
    "c_cp_StrongLocalArea3": [
      "静岡県"
    ],
    "c_cp_StrongLocalArea6": [
      "九州全般"
    ],
    "c_cp_Tags": [
      "シンガポール",
      "ハワイ",
      "母娘旅",
      "旅のしおり"
    ],
    "c_metaDescription": "JTBトラベルコンサルタント ｜ 堀田",
    "c_metaTitle": "JTBトラベルコンサルタント ｜ 堀田",
    "c_pagesURL": "https://consultants.jtb.co.jp/cp_20051320",
    "c_responsibleService": [
      "リテール店舗"
    ],
    "c_v2Folder": "10247_マークイズ静岡店",
    "name": "ほった_20051320",
    "timezone": "Asia/Tokyo"
  },
  "entityType": "ce_consultant",
  "labels": []
}