{
  "$id": "cp_20061310",
  "$schema": "https://schema.yext.com/config/km/entity/v1",
  "primaryLocale": "ja",
  "content": {
    "c_CSS": ".Core-description {\nwhite-space: pre-wrap;\n}",
    "c_cSSMobile": ".Core-description {\nwhite-space: pre-wrap;\n}",
    "c_cp_BranchOfficeRegion": "静岡県",
    "c_cp_CTA1": {
      "label": "杉山 の相談予約はこちら",
      "link": "https://jtb.rooms-online.jp/calendar/schedule/y-oDn-9Xw-arNbQgwVqkBDy",
      "linkType": "URL"
    },
    "c_cp_CTA2": {
      "label": "このコンサルタントがいる店舗の相談予約はこちら",
      "link": "https://jtb.rooms-online.jp/calendar/schedule/y-oDn-9Xw-arNbQgwVqkBDy",
      "linkType": "URL"
    },
    "c_cp_Certification": [
      "総合旅行業取扱管理者",
      "ウエディングコンサルタント"
    ],
    "c_cp_Description": "こんにちは　杉山です。\n\n3世代のご旅行や記念旅行のご提案を得意としております。大事なご旅行のご相談は安心してお任せくださいませ。\n\nクルーズでは特にダイアモンドプリンセスに数多く乗船しております。初めてのクルーズでご不安な方、いつかはクルーズに挑戦なさりたい方はぜひご相談くださいませ。\n皆さまのご来店を心よりお待ちしております。",
    "c_cp_DisplayName": "杉山",
    "c_cp_FieldOfExpertise": [
      "母娘旅",
      "夫婦旅",
      "ハネムーン",
      "記念旅行",
      "クルーズ"
    ],
    "c_cp_GeneralInfo": [
      "クルーズコンサルタント"
    ],
    "c_cp_JobTitle": "JTB三島イトーヨーカドー日清プラザ店　トラベルコンサルタント",
    "c_cp_PagesGeneration": true,
    "c_cp_Photo": {
      "height": 1013,
      "sourceUrl": "https://a.mktgcdn.com/p/IuoHgSwMbPS4HDol8hy7H9Z9cI2we5uAjrrnlohPe_Y/1072x1013.png",
      "thumbnails": [
        {
          "height": 1013,
          "url": "https://a.mktgcdn.com/p-sandbox/IuoHgSwMbPS4HDol8hy7H9Z9cI2we5uAjrrnlohPe_Y/1072x1013.png",
          "width": 1072
        },
        {
          "height": 585,
          "url": "https://a.mktgcdn.com/p-sandbox/IuoHgSwMbPS4HDol8hy7H9Z9cI2we5uAjrrnlohPe_Y/619x585.png",
          "width": 619
        },
        {
          "height": 450,
          "url": "https://a.mktgcdn.com/p-sandbox/IuoHgSwMbPS4HDol8hy7H9Z9cI2we5uAjrrnlohPe_Y/476x450.png",
          "width": 476
        },
        {
          "height": 185,
          "url": "https://a.mktgcdn.com/p-sandbox/IuoHgSwMbPS4HDol8hy7H9Z9cI2we5uAjrrnlohPe_Y/196x185.png",
          "width": 196
        }
      ],
      "url": "https://a.mktgcdn.com/p-sandbox/IuoHgSwMbPS4HDol8hy7H9Z9cI2we5uAjrrnlohPe_Y/1072x1013.png",
      "width": 1072
    },
    "c_cp_Point": "1253",
    "c_cp_StrongAbroadArea1": [
      "ハワイ",
      "グアム",
      "サイパン"
    ],
    "c_cp_StrongAbroadArea2": [
      "カナダ"
    ],
    "c_cp_StrongAbroadArea3": [
      "フランス",
      "イタリア",
      "ドイツ"
    ],
    "c_cp_StrongAbroadArea4": [
      "インドネシア・バリ島"
    ],
    "c_cp_StrongLocalArea3": [
      "静岡県"
    ],
    "c_cp_StrongLocalArea6": [
      "長崎県"
    ],
    "c_cp_Tags": [
      "ダイヤモンドプリンセス乗船歴",
      "ハワイスペシャリスト上級",
      "ハワイ・グアム",
      "三世代"
    ],
    "c_metaDescription": "JTBトラベルコンサルタント ｜ 杉山",
    "c_metaTitle": "JTBトラベルコンサルタント ｜ 杉山",
    "c_pagesURL": "https://consultants.jtb.co.jp/cp_20061310",
    "c_responsibleService": [
      "リテール店舗"
    ],
    "c_v2Folder": "10245_三島イトーヨーカドー日清プラザ店",
    "name": "すぎやま _20061310",
    "timezone": "Asia/Tokyo"
  },
  "entityType": "ce_consultant",
  "labels": []
}