{
  "$id": "cp_21169036",
  "$schema": "https://schema.yext.com/config/km/entity/v1",
  "primaryLocale": "ja",
  "content": {
    "c_CSS": ".Core-description {\nwhite-space: pre-wrap;\n}",
    "c_cSSMobile": ".Core-description {\nwhite-space: pre-wrap;\n}",
    "c_cp_BranchOfficeRegion": "京都府",
    "c_cp_CTA1": {
      "label": "小寺の来店予約はこちら",
      "link": "https://jtb.rooms-online.jp/calendar/schedule/y-oDn-9Xw-arNbQgwVqgBd",
      "linkType": "OTHER"
    },
    "c_cp_CTA2": {
      "label": "このコンサルタントがいる店舗の相談予約はこちら",
      "link": "https://jtb.rooms-online.jp/calendar/schedule/y-oDn-9Xw-arNbQgwVqgBd",
      "linkType": "URL"
    },
    "c_cp_Description": "数年前から滝の魅力に惹かれ、日本滝100選制覇に向けて頑張っております。まだまだ半分もいっておりませんが、自然の中で感じるマイナスイオンは日頃の疲れを癒してくれます。またそのあとに入る温泉は最高です！！最近では、初めて一人旅を経験し自由気ままに過ごす旅にもハマっております！　ご旅行は相談からスタートしております。私の経験を少しでもお伝えし、楽しく思い出に残るご旅行にしていただけるよう精一杯お伺いさせて頂きますので、よろしくお願いいたします。",
    "c_cp_DisplayName": "小寺",
    "c_cp_FieldOfExpertise": [
      "母娘旅",
      "一人旅",
      "ハネムーン",
      "テーマパーク",
      "ドライブ",
      "温泉・立ち寄り湯",
      "音楽ライブ"
    ],
    "c_cp_GeneralInfo": [
      "●資格：ハワイスペシャリスト・総合取扱管理者・ウエディングコンサルタント・京都検定３級"
    ],
    "c_cp_HiraganaName": "こてら",
    "c_cp_JobTitle": "JTB京都駅前店 トラベルコンサルタント",
    "c_cp_OverseasExpert": {
      "area2": {
        "rank": "bronze"
      }
    },
    "c_cp_PagesGeneration": true,
    "c_cp_Photo": {
      "height": 1739,
      "sourceUrl": "https://a.mktgcdn.com/p/9vv3LmTq6NUG8EAMpI1KI03yNSEyr4o-CC8I0GOEkJ8/1212x1739.jpg",
      "thumbnails": [
        {
          "height": 1739,
          "url": "https://a.mktgcdn.com/p-sandbox/9vv3LmTq6NUG8EAMpI1KI03yNSEyr4o-CC8I0GOEkJ8/1212x1739.jpg",
          "width": 1212
        },
        {
          "height": 888,
          "url": "https://a.mktgcdn.com/p-sandbox/9vv3LmTq6NUG8EAMpI1KI03yNSEyr4o-CC8I0GOEkJ8/619x888.jpg",
          "width": 619
        },
        {
          "height": 450,
          "url": "https://a.mktgcdn.com/p-sandbox/9vv3LmTq6NUG8EAMpI1KI03yNSEyr4o-CC8I0GOEkJ8/314x450.jpg",
          "width": 314
        },
        {
          "height": 281,
          "url": "https://a.mktgcdn.com/p-sandbox/9vv3LmTq6NUG8EAMpI1KI03yNSEyr4o-CC8I0GOEkJ8/196x281.jpg",
          "width": 196
        }
      ],
      "url": "https://a.mktgcdn.com/p-sandbox/9vv3LmTq6NUG8EAMpI1KI03yNSEyr4o-CC8I0GOEkJ8/1212x1739.jpg",
      "width": 1212
    },
    "c_cp_StrongAbroadArea1": [
      "ハワイ"
    ],
    "c_cp_StrongAbroadArea3": [
      "フランス"
    ],
    "c_cp_StrongAbroadArea4": [
      "インドネシア・バリ島",
      "シンガポール"
    ],
    "c_cp_StrongLocalArea1": [
      "北海道"
    ],
    "c_cp_StrongLocalArea2": [
      "千葉県",
      "東京都"
    ],
    "c_cp_StrongLocalArea3": [
      "北陸全般"
    ],
    "c_cp_StrongLocalArea4": [
      "近畿全般"
    ],
    "c_cp_StrongLocalArea5": [
      "中国全般",
      "四国全般"
    ],
    "c_cp_StrongLocalArea6": [
      "九州全般",
      "沖縄県"
    ],
    "c_cp_Tags": [
      "滝",
      "立ち寄り湯",
      "離島",
      "3月フランス行ってきました"
    ],
    "c_metaDescription": "JTBトラベルコンサルタント | 小寺",
    "c_metaTitle": "JTBトラベルコンサルタント | 小寺",
    "c_pagesURL": "https://consultants.jtb.co.jp/cp_21169036",
    "c_responsibleService": [
      "海外専門デスクスタッフ",
      "リテール店舗"
    ],
    "c_v2Folder": "10304_京都駅前店",
    "name": "こてら_21169036",
    "timezone": "Asia/Tokyo"
  },
  "entityType": "ce_consultant",
  "labels": []
}