{
  "$id": "cp_y_hamamoto034",
  "$schema": "https://schema.yext.com/config/km/entity/v1",
  "primaryLocale": "ja",
  "content": {
    "c_CSS": ".Core-description {\nwhite-space: pre-wrap;\n}",
    "c_cSSMobile": ".Core-description {\nwhite-space: pre-wrap;\n}",
    "c_cp_BranchOfficeRegion": "東京都",
    "c_cp_CTA1": {
      "label": "濱本の海外旅行相談予約はこちら",
      "link": "https://jtb.rooms-online.jp/calendar/schedule/y-oDn-9Xw-arNbQgwVNdBG",
      "linkType": "URL"
    },
    "c_cp_CTA2": {
      "label": "このコンサルタントがいる店舗の相談予約はこちら",
      "link": "https://jtb.rooms-online.jp/calendar/schedule/y-oDn-9Xw-arNbQkwVf7xG",
      "linkType": "URL"
    },
    "c_cp_Certification": [
      "総合旅行業取扱管理者",
      "ウエディングコンサルタント"
    ],
    "c_cp_Description": "海をのんびり眺めるのが大好きです！\n\nリゾートホテル滞在やラグジュアリーホテル好きで、ハワイ、沖縄、グアム、バリ、モルディブなどたくさんのリゾートホテルに宿泊してきましたので、滞在方も合わせてご一緒にご案内いたします。\n\nヨーロッパの街並みも大好きなので、お任せください。\n是非一緒に旅を作りましょう★\n\n国内も含めハネムーンや記念旅行もたくさんご送客してまいりましたので、お客様の叶えたいことやお気持ちを読み取りながら、丁寧にご提案いたします。特別で大切な時間を過ごすご旅行をお客様と共に作っていく時間が何よりしあわせです★是非お会いできるのを楽しみにしております。",
    "c_cp_DisplayName": "濱本",
    "c_cp_FieldOfExpertise": [
      "母娘旅",
      "夫婦旅",
      "ハネムーン",
      "記念旅行",
      "グルメ",
      "カフェ"
    ],
    "c_cp_GeneralInfo": [
      "世界遺産検定3級",
      "ハワイスペシャリスト上級",
      "クルーズコンサルタント"
    ],
    "c_cp_HiraganaName": "はまもと",
    "c_cp_JobTitle": "JTBトラベルゲート有楽町 トラベルコンサルタント",
    "c_cp_PagesGeneration": true,
    "c_cp_Photo": {
      "height": 419,
      "sourceUrl": "https://a.mktgcdn.com/p/vkgBQ4ILpYTzplSYTFkAcX0giNzBCiX_DcRLcUGDKjg/364x419.jpg",
      "thumbnails": [
        {
          "height": 419,
          "url": "https://a.mktgcdn.com/p-sandbox/pYzUhAZ-DJov7Esa6BV05sUEQd1ZgCVY3Ku0UvDJw9o/364x419.jpg",
          "width": 364
        },
        {
          "height": 226,
          "url": "https://a.mktgcdn.com/p-sandbox/pYzUhAZ-DJov7Esa6BV05sUEQd1ZgCVY3Ku0UvDJw9o/196x226.jpg",
          "width": 196
        }
      ],
      "url": "https://a.mktgcdn.com/p-sandbox/pYzUhAZ-DJov7Esa6BV05sUEQd1ZgCVY3Ku0UvDJw9o/364x419.jpg",
      "width": 364
    },
    "c_cp_Point": "193",
    "c_cp_StrongAbroadArea1": [
      "ハワイ",
      "オーストラリア",
      "ニューカレドニア"
    ],
    "c_cp_StrongAbroadArea3": [
      "フランス",
      "スペイン",
      "イタリア"
    ],
    "c_cp_StrongLocalArea1": [
      "北海道"
    ],
    "c_cp_StrongLocalArea4": [
      "京都府"
    ],
    "c_cp_StrongLocalArea6": [
      "沖縄県"
    ],
    "c_cp_Tags": [
      "2024年7月ハワイ行ってきました！",
      "イタリア渡航経験あり!ヨーロッパ好き★",
      "モルディブリゾート行ってきました",
      "ラグジュアリーホテル・ラウンジ巡り★",
      "サントリーニ島・ニューカレドニアリゾート"
    ],
    "c_metaDescription": "JTBトラベルコンサルタント | 濱本",
    "c_metaTitle": "JTBトラベルコンサルタント | 濱本",
    "c_pagesURL": "https://consultants.jtb.co.jp/cp_y_hamamoto034",
    "c_responsibleService": [
      "リテール店舗"
    ],
    "c_v2Folder": "10152_トラベルゲート有楽町",
    "name": "はまもと ようこ_17076034",
    "timezone": "Asia/Tokyo"
  },
  "entityType": "ce_consultant",
  "labels": []
}